benchmarks/__init__.py
benchmarks/benchmark.py
examples/basic_usage.py
examples/batch_generation.py
examples/database_usage.py
fastuuid7-0.1.0.dist-info/licenses/LICENSE
tests/__init__.py
tests/test_uuidv7.py
uuidv7/__init__.py
uuidv7/uuidv7/__init__.py
uuidv7/uuidv7_impl/__init__.py
uuidv7/uuidv7_impl/uuid7_gen.c
uuidv7/uuidv7_impl/uuid7_gen.cpython-313-x86_64-linux-gnu.so
uuidv7/uuidv7_impl/include/uuid7_gen.h
uuidv7/uuidv7_impl/src/uuid7_gen.c
fastuuid7-0.1.0.dist-info/METADATA
fastuuid7-0.1.0.dist-info/WHEEL
fastuuid7-0.1.0.dist-info/top_level.txt
fastuuid7-0.1.0.dist-info/RECORD
