Metadata-Version: 2.4
Name: fastuuid7
Version: 0.1.0
Summary: UUID v7 generation package using a C library
Author-email: Pavel Nekrasov <nekrasovp@gmail.com>
License: MIT
Project-URL: Homepage, https://github.com/nekrasovp/uuidv7
Project-URL: Repository, https://github.com/nekrasovp/uuidv7
Project-URL: Issues, https://github.com/nekrasovp/uuidv7/issues
Keywords: uuid,uuidv7,uuid-v7,identifier
Classifier: Programming Language :: Python :: 3
Classifier: Programming Language :: C
Classifier: Operating System :: OS Independent
Requires-Python: >=3.8
License-File: LICENSE
Provides-Extra: dev
Requires-Dist: pytest>=7.0.0; extra == "dev"
Requires-Dist: pytest-cov>=4.0.0; extra == "dev"
Requires-Dist: ruff>=0.1.0; extra == "dev"
Dynamic: license-file
